revsymg/__init__.py
revsymg/exceptions.py
revsymg/index_lib.py
revsymg/py.typed
revsymg/algorithms/__init__.py
revsymg/algorithms/graph_functions.py
revsymg/algorithms/transitive_reduction.py
revsymg/algorithms/connected_components/__init__.py
revsymg/algorithms/connected_components/cnnted_comp_id.py
revsymg/algorithms/connected_components/cnnted_comp_tool.py
revsymg/graphs/__init__.py
revsymg/graphs/_adjancy_table.py
revsymg/graphs/attributes.py
revsymg/graphs/merged_strands_graph.py
revsymg/graphs/revsym_edges.py
revsymg/graphs/revsym_graph.py
revsymg/graphs/revsym_vertices.py
revsymg/graphs/split_strands_edges.py
revsymg/graphs/split_strands_graph.py
revsymg/graphs/split_strands_vertices.py
revsymg/id_containers/__init__.py
revsymg/id_containers/abstract_ids.py
revsymg/id_containers/hashable_ids.py
revsymg/id_containers/indices_ids.py
revsymg-0.4.1.dist-info/LICENCE
revsymg-0.4.1.dist-info/METADATA
revsymg-0.4.1.dist-info/WHEEL
revsymg-0.4.1.dist-info/top_level.txt
revsymg-0.4.1.dist-info/RECORD
