Metadata-Version: 2.1
Name: revsymg
Version: 0.4.1
Summary: A python package to efficiently store oriented DNA fragments succession relationships in a directed graph. For example, succession relationships can be overlaps between two reads.
Author-email: vepain <victor.epain@laposte.net>
License: ### GNU GENERAL PUBLIC LICENSE
Project-URL: Homepage, https://gitlab.com/vepain/pyrevsymg
Project-URL: Repository, https://gitlab.com/vepain/pyrevsymg
Project-URL: Documentation, https://pyrevsymg.readthedocs.io
Project-URL: Changelog, https://pyrevsymg.readthedocs.io/en/latest/changelog.html
Keywords: Directed graph,Overlaps graph,Assembly graph
Classifier: Intended Audience :: Developers
Classifier: License :: OSI Approved :: GNU General Public License v3 or later (GPLv3+)
Classifier: Operating System :: Unix
Classifier: Programming Language :: Python :: 3.9
Classifier: Topic :: Software Development :: Libraries :: Python Modules
Requires-Python: >=3.9
License-File: LICENCE
Requires-Dist: bitarray (<2.5.0,>=2.4.0)
